hello_tea.py
lumkar_teaxyz-1.0.6.dist-info/METADATA
lumkar_teaxyz-1.0.6.dist-info/WHEEL
lumkar_teaxyz-1.0.6.dist-info/entry_points.txt
lumkar_teaxyz-1.0.6.dist-info/top_level.txt
lumkar_teaxyz-1.0.6.dist-info/RECORD
